furiosa_smi_py-2025.3.0.dist-info/METADATA
furiosa_smi_py-2025.3.0.dist-info/WHEEL
furiosa_smi_py.libs/libfuriosa_smi-e4ac7c58.so
furiosa_smi_py/__init__.py
furiosa_smi_py/furiosa_smi_py.cpython-39-x86_64-linux-gnu.so
furiosa_smi_py-2025.3.0.dist-info/RECORD
